portfoliofinder/__init__.py
portfoliofinder-0.2.4.dist-info/LICENSE
portfoliofinder-0.2.4.dist-info/METADATA
portfoliofinder-0.2.4.dist-info/WHEEL
portfoliofinder-0.2.4.dist-info/top_level.txt
portfoliofinder-0.2.4.dist-info/RECORD
