Metadata-Version: 2.1
Name: portfoliofinder
Version: 0.2.4
Summary: Tool to help find an optimal portfolio allocation
Home-page: https://github.com/asteffey/portfolio-finder
Author: Andrew Steffey
Author-email: asteffey@gmail.com
License: MIT
Platform: UNKNOWN
Classifier: Development Status :: 4 - Beta
Classifier: Intended Audience :: Developers
Classifier: License :: OSI Approved :: MIT License
Classifier: Programming Language :: Python :: 3.7
Classifier: Programming Language :: Python :: 3.8
Requires-Dist: pandas
Requires-Dist: dill
Requires-Dist: matplotlib
Requires-Dist: mplcursors
Requires-Dist: numpy
Requires-Dist: progressbar2
Requires-Dist: scipy
